{
  "id": "3012",
  "name": "Cobberilia",
  "description": "Rank Rare. Weather Snow. Resource 332313 MCASH",
  "image": "https://raw.githubusercontent.com/sn-ntu/mcashchain-assets/master/tokens/mainnet/M721-MASPHERE/3012.png",
  "metadata": "{\"ID\":\"3012\",\"Name\":\"Cobberilia\",\"Rank\":\"Rare\",\"EarlyBird\":\"2.25%\",\"MCASH\":\"332313\",\"GMT_sum\":\"23.982\",\"Weather\":\"Snow\",\"OriginalBuyer\":\"0x842461f0e4fdd2d74653e6b7873912f3e944a41d\",\"Tier\":\"3\",\"Type\":\"4\",\"Seed2\":\"114.80%\",\"GMT_tree\":\"11.48\",\"Seed3\":\"102.20%\",\"GMT_mineral\":\"11.480\",\"Description\":\"Rank Rare. Weather Snow. Resource 332313 MCASH\",\"Image\":\"https://raw.githubusercontent.com/sn-ntu/mcashchain-assets/master/tokens/mainnet/M721-MASPHERE/3012.png\"}"
}
